plucker/__init__.py
plucker/exceptions.py
plucker/extractor.py
plucker/plucker.py
plucker/py.typed
plucker/tokeniser.py
plucker/types.py
plucker-0.1.0.dist-info/LICENSE
plucker-0.1.0.dist-info/WHEEL
plucker-0.1.0.dist-info/METADATA
plucker-0.1.0.dist-info/RECORD
