Metadata-Version: 2.1
Name: plucker
Version: 0.1.0
Summary: Validate and extract JSON-sourced data into type-safe dataclasses
Home-page: https://github.com/takkaria/plucker
License: MIT
Author: Anna Sidwell
Author-email: anna@takkaria.org
Requires-Python: >=3.7,<4.0
Classifier: Development Status :: 3 - Alpha
Classifier: Intended Audience :: Developers
Classifier: License :: OSI Approved :: MIT License
Classifier: Operating System :: OS Independent
Classifier: Programming Language :: Python :: 3
Classifier: Programming Language :: Python :: 3.7
Classifier: Programming Language :: Python :: 3.8
Classifier: Programming Language :: Python :: 3.9
Classifier: Topic :: Software Development :: Libraries :: Python Modules
Project-URL: Repository, https://github.com/takkaria/plucker
